valer.lims-1.3.4rc11-nspkg.pth
senaite/lims/__init__.py
senaite/lims/config.py
senaite/lims/configure.zcml
senaite/lims/interfaces.py
senaite/lims/setuphandlers.py
senaite/lims/profiles/default/metadata.xml
senaite/lims/profiles/default/senaite.lims.txt
senaite/lims/tests/__init__.py
senaite/lims/tests/base.py
senaite/lims/tests/test_doctests.py
senaite/lims/tests/test_setup.py
senaite/lims/upgrades/__init__.py
senaite/lims/upgrades/configure.zcml
senaite/lims/upgrades/handlers.py
valer.lims-1.3.4rc11.dist-info/DESCRIPTION.rst
valer.lims-1.3.4rc11.dist-info/METADATA
valer.lims-1.3.4rc11.dist-info/RECORD
valer.lims-1.3.4rc11.dist-info/WHEEL
valer.lims-1.3.4rc11.dist-info/entry_points.txt
valer.lims-1.3.4rc11.dist-info/metadata.json
valer.lims-1.3.4rc11.dist-info/namespace_packages.txt
valer.lims-1.3.4rc11.dist-info/top_level.txt
